almasru/__init__.py
almasru/briefrecord.py
almasru/client.py
almasru/common.py
almasru/configlog.py
almasru/dedup.py
almasru/utils.py
almasru/version.py
almasru-3.0.3.dist-info/licenses/licence.txt
almasru-3.0.3.dist-info/METADATA
almasru-3.0.3.dist-info/WHEEL
almasru-3.0.3.dist-info/top_level.txt
almasru-3.0.3.dist-info/RECORD
