Metadata-Version: 2.4
Name: almasru
Version: 3.0.3
Summary: This python module is a tool to use Alma SRU. it manages the logs and the backup of the records.
Author-email: Raphaël Rey <raphael.rey@slsp.ch>
Project-URL: Homepage, https://github.com/Swiss-Library-Service-Platform/almasru
Project-URL: Bug Tracker, https://github.com/Swiss-Library-Service-Platform/almasru/issues
Classifier: Programming Language :: Python :: 3
Classifier: Operating System :: OS Independent
Requires-Python: >=3
License-File: licence.txt
Requires-Dist: requests
Requires-Dist: lxml
Requires-Dist: openpyxl
Requires-Dist: numpy
Requires-Dist: pandas
Requires-Dist: Levenshtein
Dynamic: license-file
